policyengine/__init__.py
policyengine/__pycache__/__init__.cpython-313.pyc
policyengine/core/__init__.py
policyengine/core/cache.py
policyengine/core/dataset.py
policyengine/core/dataset_version.py
policyengine/core/dynamic.py
policyengine/core/output.py
policyengine/core/parameter.py
policyengine/core/parameter_value.py
policyengine/core/policy.py
policyengine/core/simulation.py
policyengine/core/tax_benefit_model.py
policyengine/core/tax_benefit_model_version.py
policyengine/core/variable.py
policyengine/outputs/__init__.py
policyengine/outputs/aggregate.py
policyengine/outputs/change_aggregate.py
policyengine/outputs/decile_impact.py
policyengine/outputs/inequality.py
policyengine/outputs/poverty.py
policyengine/tax_benefit_models/uk.py
policyengine/tax_benefit_models/us.py
policyengine/tax_benefit_models/uk/__init__.py
policyengine/tax_benefit_models/uk/analysis.py
policyengine/tax_benefit_models/uk/datasets.py
policyengine/tax_benefit_models/uk/model.py
policyengine/tax_benefit_models/uk/outputs.py
policyengine/tax_benefit_models/us/__init__.py
policyengine/tax_benefit_models/us/analysis.py
policyengine/tax_benefit_models/us/datasets.py
policyengine/tax_benefit_models/us/model.py
policyengine/tax_benefit_models/us/outputs.py
policyengine/utils/__init__.py
policyengine/utils/dates.py
policyengine/utils/parameter_labels.py
policyengine/utils/parametric_reforms.py
policyengine/utils/plotting.py
policyengine-3.1.16.dist-info/licenses/LICENSE
policyengine-3.1.16.dist-info/METADATA
policyengine-3.1.16.dist-info/WHEEL
policyengine-3.1.16.dist-info/top_level.txt
policyengine-3.1.16.dist-info/RECORD
