Metadata-Version: 2.4
Name: policyengine
Version: 3.1.16
Summary: A package to conduct policy analysis using PolicyEngine tax-benefit models.
Author-email: PolicyEngine <hello@policyengine.org>
License:                     GNU AFFERO GENERAL PUBLIC LICENSE
Requires-Python: >=3.13
License-File: LICENSE
Requires-Dist: pydantic>=2.0.0
Requires-Dist: pandas>=2.0.0
Requires-Dist: microdf_python>=1.2.1
Requires-Dist: plotly>=5.0.0
Requires-Dist: requests>=2.31.0
Requires-Dist: psutil>=5.9.0
Provides-Extra: uk
Requires-Dist: policyengine_core>=3.23.6; extra == "uk"
Requires-Dist: policyengine-uk>=2.51.0; extra == "uk"
Provides-Extra: us
Requires-Dist: policyengine_core>=3.23.6; extra == "us"
Requires-Dist: policyengine-us>=1.213.1; extra == "us"
Provides-Extra: dev
Requires-Dist: black; extra == "dev"
Requires-Dist: pytest; extra == "dev"
Requires-Dist: furo; extra == "dev"
Requires-Dist: autodoc_pydantic; extra == "dev"
Requires-Dist: jupyter-book; extra == "dev"
Requires-Dist: yaml-changelog>=0.1.7; extra == "dev"
Requires-Dist: itables; extra == "dev"
Requires-Dist: build; extra == "dev"
Requires-Dist: pytest-asyncio>=0.26.0; extra == "dev"
Requires-Dist: ruff>=0.5.0; extra == "dev"
Requires-Dist: policyengine_core>=3.23.6; extra == "dev"
Requires-Dist: policyengine-uk>=2.51.0; extra == "dev"
Requires-Dist: policyengine-us>=1.213.1; extra == "dev"
Dynamic: license-file
